ori/__init__.py
ori/asyncio.py
ori/concurrency.py
ori/errors.py
ori/poolchain.py
ori/subprocess.py
ori-0.1.2.dist-info/LICENSE
ori-0.1.2.dist-info/WHEEL
ori-0.1.2.dist-info/METADATA
ori-0.1.2.dist-info/RECORD
