Metadata-Version: 2.1
Name: ori
Version: 0.1.2
Summary: Concurrency tools for Python.
License: MIT
Author: James Mishra
Author-email: james.mishra@neocrym.com
Requires-Python: >=3.7
Classifier: License :: OSI Approved :: MIT License
Classifier: Programming Language :: Python :: 3
Classifier: Programming Language :: Python :: 3.7
Classifier: Programming Language :: Python :: 3.8
